ecotransformers/__init__.py
ecotransformers/main.py
ecotransformers-1.0.0.dist-info/LICENCE
ecotransformers-1.0.0.dist-info/METADATA
ecotransformers-1.0.0.dist-info/WHEEL
ecotransformers-1.0.0.dist-info/entry_points.txt
ecotransformers-1.0.0.dist-info/top_level.txt
ecotransformers-1.0.0.dist-info/RECORD
