Metadata-Version: 2.1
Name: ecotransformers
Version: 1.0.0
Summary: Towards Net-Zero AI: Reducing Latency and Energy Consumption with Eco-Transformers
Home-page: https://github.com/aarthyviven/ecotransformers
Author: ['Shriaarthy E', 'Sangeetha S']
License: MIT
Platform: UNKNOWN
Requires-Python: >=3.8
License-File: LICENCE
Requires-Dist: torch>=1.13.0
Requires-Dist: transformers>=4.30.0
Requires-Dist: codecarbon>=2.2.2
Requires-Dist: evaluate>=0.4.0
Requires-Dist: numpy>=1.24.0
Requires-Dist: rouge-score>=0.1.2
Requires-Dist: nltk>=3.8.0
Requires-Dist: absl-py>=1.4.0
